pypvs/__init__.py
pypvs/_version.py
pypvs/const.py
pypvs/exceptions.py
pypvs/firmware.py
pypvs/pvs.py
pypvs/pvs_fcgi.py
pypvs/models/__init__.py
pypvs/models/common.py
pypvs/models/ess.py
pypvs/models/gateway.py
pypvs/models/inverter.py
pypvs/models/meter.py
pypvs/models/pvs.py
pypvs/models/transfer_switch.py
pypvs/updaters/__init__.py
pypvs/updaters/base.py
pypvs/updaters/ess.py
pypvs/updaters/gateway.py
pypvs/updaters/meter.py
pypvs/updaters/production_inverters.py
pypvs/updaters/transfer_switch.py
pypvs-0.2.7.dist-info/licenses/LICENSE
pypvs-0.2.7.dist-info/METADATA
pypvs-0.2.7.dist-info/WHEEL
pypvs-0.2.7.dist-info/top_level.txt
pypvs-0.2.7.dist-info/RECORD
