Metadata-Version: 2.4
Name: pypvs
Version: 0.2.7
Summary: A Python package that exposes data and commands for a SunStrong Management PVS6 gateway.
Author-email: Aleksandar Mitev <amitev@sunstrongmanagement.com>
License-Expression: MIT
Project-URL: Homepage, https://github.com/SunStrong-Management/pypvs
Project-URL: Issues, https://github.com/SunStrong-Management/pypvs/issues
Classifier: Programming Language :: Python :: 3
Classifier: Operating System :: OS Independent
Requires-Python: >=3.6
License-File: LICENSE
Requires-Dist: aiohttp
Dynamic: license-file
